kitagentsdk/__init__.py
kitagentsdk/agent.py
kitagentsdk/callbacks.py
kitagentsdk/cli.py
kitagentsdk/context.py
kitagentsdk/helpers.py
kitagentsdk/kit.py
kitagentsdk/templates/.gitignore.template
kitagentsdk/templates/Makefile.template
kitagentsdk/templates/README.md.template
kitagentsdk/templates/main.py.template
kitagentsdk/templates/manifest.json.template
kitagentsdk/templates/requirements.txt.template
kitagentsdk-0.3.4.dist-info/licenses/LICENSE
kitagentsdk-0.3.4.dist-info/METADATA
kitagentsdk-0.3.4.dist-info/WHEEL
kitagentsdk-0.3.4.dist-info/entry_points.txt
kitagentsdk-0.3.4.dist-info/top_level.txt
kitagentsdk-0.3.4.dist-info/RECORD
