Metadata-Version: 2.4
Name: kitagentsdk
Version: 0.3.4
Summary: SDK and CLI for building Kit platform agents.
Classifier: Programming Language :: Python :: 3
Classifier: Programming Language :: Python :: 3 :: Only
Classifier: License :: Other/Proprietary License
Classifier: Operating System :: OS Independent
Requires-Python: >=3.10
License-File: LICENSE
Requires-Dist: requests==2.32.3
Requires-Dist: stable-baselines3==2.2.1
Dynamic: license-file
